{
    "home": {
        "text": "Home",
        "description": "Full Stack Developer"
    },
    "user": {
        "text": "About me",
        "description": "Bachelor's degree in Software Engineering with over 4 years of experience in web development, specializing in both frontend and backend. In 2021, together with my team, I developed an innovative solution that earned us first place in a <a href=\"https://www.facebook.com/hackathonVirtualReactivatePeru\" target=\"_blank\">Virtual Hackathon (#ReactivatePerú)</a>, demonstrating our ability to work under pressure, collaborate effectively, and solve complex problems. Proficient in solving complex challenges and implementing significant improvements for the companies I have worked with. Skilled in various technologies and frameworks, delivering innovative and efficient solutions that optimize processes and create value. I stand out for my proactive approach, strong technical skills, and ability to adapt to dynamic environments.",
        "hackaton": "Virtual Hackathon",
        "bachelor": "Bachelor's degree"
    },
    "project": {
        "text": "Projects",
        "sector": [
            {
                "id": 0,
                "text": "All"
            },
            {
                "id": 1,
                "text": "Automobiles"
            },
            {
                "id": 2,
                "text": "Beauty and Personal Care"
            },
            {
                "id": 3,
                "text": "Education"
            },
            {
                "id": 4,
                "text": "Media and Communication"
            },
            {
                "id": 5,
                "text": "Financial Services"
            },
            {
                "id": 6,
                "text": "Telecommunications and Technology"
            },
            {
                "id": 7,
                "text": "Professional Services"
            }
        ],
        "openCard": "Show more",
        "closeCard": "Show less",
        "liveText": "Live",
        "nameLabel": "Technology",
        "sectorLabel": "Sector",
        "noRecords": "There are no projects that match your search"
    },
    "skills": {
        "text": "Skills",
        "experience": "Comparison of years of experience by",
        "proficiency": "Comparison of years of proficiency in training by",
        "categories": [
            {
                "id": 0,
                "text": "All"
            },
            {
                "id": 1,
                "text": "Programming language"
            },
            {
                "id": 2,
                "text": "Frontend"
            },
            {
                "id": 3,
                "text": "Backend"
            },
            {
                "id": 4,
                "text": "Database"
            },
            {
                "id": 5,
                "text": "Videogames"
            },
            {
                "id": 6,
                "text": "Others"
            }
        ],
        "table":{
            "header": [
                {
                    "id": 0,
                    "text": "Logo"
                },
                {
                    "id": 1,
                    "text": "Technology"
                },
                {
                    "id": 2,
                    "text": "Category"
                },
                {
                    "id": 3,
                    "text": "Years of experience"
                },
                {
                    "id": 4,
                    "text": "Work Experience"
                }
            ],
            "experienceLabel": "Job Experience",
            "experienceOptions": [
                {
                    "id": 0,
                    "text": "All"
                },
                {
                    "id": 1,
                    "text": "With experience"
                },
                {
                    "id": 2,
                    "text": "Without experience"
                }
            ],
            "categoryLabel": "Category",
            "nameLabel": "Technology",
            "yearsLabel": "Years",
            "footer": {
                "noRecords": "No results found",
                "showRows": "Showing {start} to {end} of {total}"
            }
        },
        "openGraphic": "Show graphics",
        "closeGraphic": "Hide graphics"
    },
    "contact": {
        "text": "Get in touch",
        "snackbard": {
            "copy": "Copied!"
        }
    },
    "footer":{
        "text": "All rights reserved"
    }
}